<annotation>
	<folder>03_Gnorimus_variabilis</folder>
	<filename>Ceton_Gnorimus_variabilisCeton_Cetonia_kemalibiolib_cz10058.jpg</filename>
	<path>C:\Users\Gokhan GOK\Google Drive\YlisansBiyoloji\01Cetoniinae\01_Cetonia_aurata\Ceton_Gnorimus_variabilisCeton_Cetonia_kemalibiolib_cz10058.xml</path>
	<source>
		<database>Unknown</database>
	</source>
	<size>
		<width>680</width>
		<height>510</height>
		<depth>3</depth>
	</size>
	<segmented>0</segmented>
	<object>
		<name>Gnorimus_variabilis</name>
		<pose>Unspecified</pose>
		<truncated>0</truncated>
		<difficult>0</difficult>
		<bndbox>
			<xmin>130</xmin>
			<ymin>33</ymin>
			<xmax>567</xmax>
			<ymax>473</ymax>
		</bndbox>
	</object>
</annotation>