<annotation>
	<folder>06_Oxythyrea_funesta</folder>
	<filename>20190425_151440.jpg</filename>
	<path>C:\Users\Gokhan GOK\Google Drive\YlisansBiyoloji\01Cetoniinae\06_Oxythyrea_funesta\20190425_151440.jpg</path>
	<source>
		<database>Unknown</database>
	</source>
	<size>
		<width>1024</width>
		<height>768</height>
		<depth>3</depth>
	</size>
	<segmented>0</segmented>
	<object>
		<name>Oxythyrea_funesta</name>
		<pose>Unspecified</pose>
		<truncated>0</truncated>
		<difficult>0</difficult>
		<bndbox>
			<xmin>378</xmin>
			<ymin>330</ymin>
			<xmax>525</xmax>
			<ymax>423</ymax>
		</bndbox>
	</object>
</annotation>
