<annotation>
	<folder>04Chrysolina_oricalcia</folder>
	<filename>Coleop_Chrysolina_oricalcia20190426_153530.jpg</filename>
	<path>C:\Users\Asus\Google Drive\ylisansbiyoloji\02Coleoptera\04Chrysolina_oricalcia\Coleop_Chrysolina_oricalcia20190426_153530.jpg</path>
	<source>
		<database>Unknown</database>
	</source>
	<size>
		<width>1024</width>
		<height>768</height>
		<depth>3</depth>
	</size>
	<segmented>0</segmented>
	<object>
		<name>Chrysolina_oricalcia</name>
		<pose>Unspecified</pose>
		<truncated>0</truncated>
		<difficult>0</difficult>
		<bndbox>
			<xmin>488</xmin>
			<ymin>302</ymin>
			<xmax>604</xmax>
			<ymax>405</ymax>
		</bndbox>
	</object>
	<object>
		<name>Chrysolina_oricalcia</name>
		<pose>Unspecified</pose>
		<truncated>0</truncated>
		<difficult>0</difficult>
		<bndbox>
			<xmin>339</xmin>
			<ymin>412</ymin>
			<xmax>436</xmax>
			<ymax>492</ymax>
		</bndbox>
	</object>
	<object>
		<name>Chrysolina_oricalcia</name>
		<pose>Unspecified</pose>
		<truncated>0</truncated>
		<difficult>0</difficult>
		<bndbox>
			<xmin>477</xmin>
			<ymin>437</ymin>
			<xmax>603</xmax>
			<ymax>534</ymax>
		</bndbox>
	</object>
	<object>
		<name>Chrysolina_oricalcia</name>
		<pose>Unspecified</pose>
		<truncated>0</truncated>
		<difficult>0</difficult>
		<bndbox>
			<xmin>338</xmin>
			<ymin>287</ymin>
			<xmax>454</xmax>
			<ymax>355</ymax>
		</bndbox>
	</object>
	<object>
		<name>Chrysolina_oricalcia</name>
		<pose>Unspecified</pose>
		<truncated>0</truncated>
		<difficult>0</difficult>
		<bndbox>
			<xmin>347</xmin>
			<ymin>555</ymin>
			<xmax>458</xmax>
			<ymax>660</ymax>
		</bndbox>
	</object>
	<object>
		<name>Chrysolina_oricalcia</name>
		<pose>Unspecified</pose>
		<truncated>0</truncated>
		<difficult>0</difficult>
		<bndbox>
			<xmin>493</xmin>
			<ymin>566</ymin>
			<xmax>632</xmax>
			<ymax>690</ymax>
		</bndbox>
	</object>
</annotation>
